trial_rohit/__init__.py
trial_rohit/trial_rohit01.py
trial_rohit01-0.0.1.dist-info/LICENSE
trial_rohit01-0.0.1.dist-info/METADATA
trial_rohit01-0.0.1.dist-info/WHEEL
trial_rohit01-0.0.1.dist-info/top_level.txt
trial_rohit01-0.0.1.dist-info/RECORD
