Metadata-Version: 2.1
Name: trial-rohit01
Version: 0.0.1
Author: rohit
Author-email: rk0901308@gmail.com
License: MIT
Classifier: Programming Language :: Python :: 3
Classifier: License :: OSI Approved :: MIT License
Classifier: Operating System :: OS Independent
License-File: LICENSE
Requires-Dist: numpy
